CHANGELOG.txt
LICENCE.txt
MANIFEST.in
README.txt
setup.py
okrasoup.egg-info/PKG-INFO
okrasoup.egg-info/SOURCES.txt
okrasoup.egg-info/dependency_links.txt
okrasoup.egg-info/top_level.txt
prudhvicalculator/__init__.py